COSE221_Digital_Logic_Design/Lab #4/gates.sv
/* *******************************
 *	COSE221 Lab #4
 *
 *	Author: Gunjae Koo (gunjaekoo@korea.ac.kr)
 *
 * *******************************
 */

// This file includes basic gates required for design strcutural modesl
// You should use only the following modules for your design
// Available gates: xor2, and2, or2, and3, or3, and4, or4

`timescale 1ns/1ps
module xor2 (
	input	logic	a, b,
	output	logic	y
);
	assign #(0.010) y = a ^ b;	// delay: 10 ps
endmodule

module and2 (
	input	logic	a, b,
	output	logic	y
);
	assign #(0.015) y = a & b;	// delay: 15 ps
endmodule

module or2 (
	input	logic	a, b,
	output	logic	y
);
	assign #(0.015) y = a | b;	// delay: 15 ps
endmodule

module and3 (
	input	logic	a, b, c,
	output	logic	y
);
	assign #(0.016) y = a & b & c;	// delay: 16 ps
endmodule

module or3 (
	input	logic	a, b, c,
	output	logic	y
);
	assign #(0.016) y = a | b | c;	// delay: 16 ps
endmodule

module and4 (
	input	logic	a, b, c, d,
	output	logic	y
);
	assign #(0.017) y = a & b & c & d;	// delay: 17 ps
endmodule

module or4 (
	input	logic	a, b, c, d,
	output	logic	y
);
	assign #(0.017) y = a | b | c | d;	// delay: 17 ps
endmodule

COSE221_Digital_Logic_Design/Lab #4/rca16.sv
/* *******************************
 *	COSE221 Lab #4
 *
 *	Author: Gunjae Koo (gunjaekoo@korea.ac.kr)
 *
 * *******************************
 */

`timescale 1ns/1ps
// full adder (structural module)
module fadd (
	input	logic	a, b, cin,
	output	logic	s, cout
);

	logic 	[3:0]	n;	// internal nodes

	// sum: s = (a ^ b) ^ cin
	xor2 u_xor2_0(a, b, n[0]);
	xor2 u_xor2_1(n[0], cin, s);

	// cout: cout = (a*b) + (a*cin) + (b*cin)
	and2 u_and2_0(a, b, n[1]);
	and2 u_and2_1(a, cin, n[2]);
	and2 u_and2_2(b, cin, n[3]);
	or3 u_or3_0(n[1], n[2], n[3], cout);


endmodule

module rca16 (
	input					clk, rst_b,
	input	logic [15:0]	a, b, 
	input	logic			cin,
	output	logic [15:0]	s,
	output	logic			cout
);

	// registers for input signals
	logic	[15:0]	a_q, b_q;
	logic			cin_q;

	// t_pcq of D flip-flop is 0.010 ns
	always_ff @ (posedge clk or negedge rst_b) begin
		if (~rst_b) begin
			a_q <= 'b0;
			b_q <= 'b0;
			cin_q <= 'b0;
		end else begin
			a_q <= #(0.010) a;
			b_q <= #(0.010) b;
			cin_q <= #(0.010) cin;
		end
	end

	logic 	[15:0]	c;		// internal nodes (carry)
	logic	[15:0]	s_w;	// sum (output of an adder)

	fadd	u_fadd_0	(a_q[0], b_q[0], cin_q, s_w[0], c[0]);
	fadd	u_fadd_1	(a_q[1], b_q[1], c[0], s_w[1], c[1]);
	fadd	u_fadd_2	(a_q[2], b_q[2], c[1], s_w[2], c[2]);
	fadd	u_fadd_3	(a_q[3], b_q[3], c[2], s_w[3], c[3]);
	fadd	u_fadd_4	(a_q[4], b_q[4], c[3], s_w[4], c[4]);
	fadd	u_fadd_5	(a_q[5], b_q[5], c[4], s_w[5], c[5]);
	fadd	u_fadd_6	(a_q[6], b_q[6], c[5], s_w[6], c[6]);
	fadd	u_fadd_7	(a_q[7], b_q[7], c[6], s_w[7], c[7]);
	fadd	u_fadd_8	(a_q[8], b_q[8], c[7], s_w[8], c[8]);
	fadd	u_fadd_9	(a_q[9], b_q[9], c[8], s_w[9], c[9]);
	fadd	u_fadd_10	(a_q[10], b_q[10], c[9], s_w[10], c[10]);
	fadd	u_fadd_11	(a_q[11], b_q[11], c[10], s_w[11], c[11]);
	fadd	u_fadd_12	(a_q[12], b_q[12], c[11], s_w[12], c[12]);
	fadd	u_fadd_13	(a_q[13], b_q[13], c[12], s_w[13], c[13]);
	fadd	u_fadd_14	(a_q[14], b_q[14], c[13], s_w[14], c[14]);
	fadd	u_fadd_15	(a_q[15], b_q[15], c[14], s_w[15], c[15]);


	// registers for output signals
	always_ff @ (posedge clk or negedge rst_b) begin
		if (~rst_b) begin
			s <= 'b0;
			cout <= 'b0;
		end else begin
			s <= #(0.010) s_w;
			cout <= #(0.010) c[15];
		end
	end

endmodule

COSE221_Digital_Logic_Design/Lab #4/tb_rca16.sv
/* ************************
 *	COSE221 Lab #4
 *
 *	Author: Gunjae Koo (gunjaekoo2@korea.ac.kr)
 * ************************
 */

`timescale 1ns/1ps
`define CLK_T 0.505 	// 0.505 미만으로는 INCORRECT 를 받음
`define FF 0.001
module tb_rca16();

	integer f;
	logic 		clk, rst_b;

	initial clk = 1'b1;
	always #(`CLK_T/2.0) clk = ~clk;

	logic	[15:0]	a, b;
	logic	[15:0]	a_d1, b_d1;
	logic	[15:0]	a_d2, b_d2;
	logic			cin, cin_d1, cin_d2;
	logic	[15:0]	s, s_gold;
	logic			cout, cout_gold;

	initial begin
		$dumpfile("tb_rca16.vcd");
		$dumpvars(0, tb_rca16);
		f = $fopen("tb_rca16.out", "w");
		
		rst_b = 1'b0;
		a = 'b0; b = 'b0; cin = 'b0;
		a_d1 = 'b0; b_d1 = 'b0; cin_d1 = 'b0;
		a_d2 = 'b0; b_d2 = 'b0; cin_d2 = 'b0;
		repeat (2) @ (posedge clk);
		#(`FF) rst_b = 1'b1;
		repeat (2) @ (posedge clk);
		#(`FF) a = 16'h0000; b = 16'hFFFF; cin = 1'b0;
		@ (posedge clk);
		#(`FF) a = 16'h0000; b = 16'hFFFF; cin = 1'b1;

		repeat (1024) begin
			@ (posedge clk);
			#(`FF) a = a + 1;
		end
		repeat (1024) begin
			@ (posedge clk);
			#(`FF) b = b + 1;
		end
		
		repeat (2) @ (posedge clk);
		$fclose(f);
		$finish(1);
	end

	always @ (posedge clk) begin
		a_d1 <= #(`FF) a;
		b_d1 <= #(`FF) b;
		cin_d1 <= #(`FF) cin;
		
		a_d2 <= #(`FF) a_d1;
		b_d2 <= #(`FF) b_d1;
		cin_d2 <= #(`FF) cin_d1;
	end

	assign {cout_gold, s_gold} = {1'b0, a_d2} + b_d2 + cin_d2;

	always @ (negedge clk) begin
		if (s!==s_gold || cout!==cout_gold) begin
			$write("Golden: %04x + %04x + %1b = {%1b, %04x}\t", a_d2, b_d2, cin_d2, cout_gold, s_gold);
			$write("DUT: {%1b, %04x}\t", cout, s);
			$write("Incorrect!!");
			$write("\n");
		end
		
		$fwrite(f, "Golden: %04x + %04x + %1b = {%1b, %04x}\t", a_d2, b_d2, cin_d2, cout_gold, s_gold);
		$fwrite(f, "DUT: {%1b, %04x}\t", cout, s);
		if (s!==s_gold || cout!==cout_gold) $fwrite(f, "Incorrect!!");
		$fwrite(f, "\n");
	end

	rca16	dut	(clk, rst_b, a, b, cin, s, cout);

endmodule

COSE221_Digital_Logic_Design/Lab #4/tb_rca16.vcd
$date
	Sun Jun 11 23:56:37 2023
$end
$version
	Icarus Verilog
$end
$timescale
	1ps
$end
$scope module tb_rca16 $end
$var wire 16 ! s_gold [15:0] $end
$var wire 16 " s [15:0] $end
$var wire 1 # cout_gold $end
$var wire 1 $ cout $end
$var reg 16 % a [15:0] $end
$var reg 16 & a_d1 [15:0] $end
$var reg 16 ' a_d2 [15:0] $end
$var reg 16 ( b [15:0] $end
$var reg 16 ) b_d1 [15:0] $end
$var reg 16 * b_d2 [15:0] $end
$var reg 1 + cin $end
$var reg 1 , cin_d1 $end
$var reg 1 - cin_d2 $end
$var reg 1 . clk $end
$var reg 1 / rst_b $end
$var integer 32 0 f [31:0] $end
$scope module dut $end
$var wire 16 1 a [15:0] $end
$var wire 16 2 b [15:0] $end
$var wire 1 + cin $end
$var wire 1 . clk $end
$var wire 1 / rst_b $end
$var wire 16 3 s_w [15:0] $end
$var wire 16 4 c [15:0] $end
$var reg 16 5 a_q [15:0] $end
$var reg 16 6 b_q [15:0] $end
$var reg 1 7 cin_q $end
$var reg 1 $ cout $end
$var reg 16 8 s [15:0] $end
$scope module u_fadd_0 $end
$var wire 1 9 a $end
$var wire 1 : b $end
$var wire 1 7 cin $end
$var wire 1 ; s $end
$var wire 4 < n [3:0] $end
$var wire 1 = cout $end
$scope module u_and2_0 $end
$var wire 1 9 a $end
$var wire 1 : b $end
$var wire 1 > y $end
$upscope $end
$scope module u_and2_1 $end
$var wire 1 9 a $end
$var wire 1 7 b $end
$var wire 1 ? y $end
$upscope $end
$scope module u_and2_2 $end
$var wire 1 : a $end
$var wire 1 7 b $end
$var wire 1 @ y $end
$upscope $end
$scope module u_or3_0 $end
$var wire 1 A a $end
$var wire 1 B b $end
$var wire 1 C c $end
$var wire 1 = y $end
$upscope $end
$scope module u_xor2_0 $end
$var wire 1 9 a $end
$var wire 1 : b $end
$var wire 1 D y $end
$upscope $end
$scope module u_xor2_1 $end
$var wire 1 E a $end
$var wire 1 7 b $end
$var wire 1 ; y $end
$upscope $end
$upscope $end
$scope module u_fadd_1 $end
$var wire 1 F a $end
$var wire 1 G b $end
$var wire 1 H cin $end
$var wire 1 I s $end
$var wire 4 J n [3:0] $end
$var wire 1 K cout $end
$scope module u_and2_0 $end
$var wire 1 F a $end
$var wire 1 G b $end
$var wire 1 L y $end
$upscope $end
$scope module u_and2_1 $end
$var wire 1 F a $end
$var wire 1 H b $end
$var wire 1 M y $end
$upscope $end
$scope module u_and2_2 $end
$var wire 1 G a $end
$var wire 1 H b $end
$var wire 1 N y $end
$upscope $end
$scope module u_or3_0 $end
$var wire 1 O a $end
$var wire 1 P b $end
$var wire 1 Q c $end
$var wire 1 K y $end
$upscope $end
$scope module u_xor2_0 $end
$var wire 1 F a $end
$var wire 1 G b $end
$var wire 1 R y $end
$upscope $end
$scope module u_xor2_1 $end
$var wire 1 S a $end
$var wire 1 H b $end
$var wire 1 I y $end
$upscope $end
$upscope $end
$scope module u_fadd_10 $end
$var wire 1 T a $end
$var wire 1 U b $end
$var wire 1 V cin $end
$var wire 1 W s $end
$var wire 4 X n [3:0] $end
$var wire 1 Y cout $end
$scope module u_and2_0 $end
$var wire 1 T a $end
$var wire 1 U b $end
$var wire 1 Z y $end
$upscope $end
$scope module u_and2_1 $end
$var wire 1 T a $end
$var wire 1 V b $end
$var wire 1 [ y $end
$upscope $end
$scope module u_and2_2 $end
$var wire 1 U a $end
$var wire 1 V b $end
$var wire 1 \ y $end
$upscope $end
$scope module u_or3_0 $end
$var wire 1 ] a $end
$var wire 1 ^ b $end
$var wire 1 _ c $end
$var wire 1 Y y $end
$upscope $end
$scope module u_xor2_0 $end
$var wire 1 T a $end
$var wire 1 U b $end
$var wire 1 ` y $end
$upscope $end
$scope module u_xor2_1 $end
$var wire 1 a a $end
$var wire 1 V b $end
$var wire 1 W y $end
$upscope $end
$upscope $end
$scope module u_fadd_11 $end
$var wire 1 b a $end
$var wire 1 c b $end
$var wire 1 d cin $end
$var wire 1 e s $end
$var wire 4 f n [3:0] $end
$var wire 1 g cout $end
$scope module u_and2_0 $end
$var wire 1 b a $end
$var wire 1 c b $end
$var wire 1 h y $end
$upscope $end
$scope module u_and2_1 $end
$var wire 1 b a $end
$var wire 1 d b $end
$var wire 1 i y $end
$upscope $end
$scope module u_and2_2 $end
$var wire 1 c a $end
$var wire 1 d b $end
$var wire 1 j y $end
$upscope $end
$scope module u_or3_0 $end
$var wire 1 k a $end
$var wire 1 l b $end
$var wire 1 m c $end
$var wire 1 g y $end
$upscope $end
$scope module u_xor2_0 $end
$var wire 1 b a $end
$var wire 1 c b $end
$var wire 1 n y $end
$upscope $end
$scope module u_xor2_1 $end
$var wire 1 o a $end
$var wire 1 d b $end
$var wire 1 e y $end
$upscope $end
$upscope $end
$scope module u_fadd_12 $end
$var wire 1 p a $end
$var wire 1 q b $end
$var wire 1 r cin $end
$var wire 1 s s $end
$var wire 4 t n [3:0] $end
$var wire 1 u cout $end
$scope module u_and2_0 $end
$var wire 1 p a $end
$var wire 1 q b $end
$var wire 1 v y $end
$upscope $end
$scope module u_and2_1 $end
$var wire 1 p a $end
$var wire 1 r b $end
$var wire 1 w y $end
$upscope $end
$scope module u_and2_2 $end
$var wire 1 q a $end
$var wire 1 r b $end
$var wire 1 x y $end
$upscope $end
$scope module u_or3_0 $end
$var wire 1 y a $end
$var wire 1 z b $end
$var wire 1 { c $end
$var wire 1 u y $end
$upscope $end
$scope module u_xor2_0 $end
$var wire 1 p a $end
$var wire 1 q b $end
$var wire 1 | y $end
$upscope $end
$scope module u_xor2_1 $end
$var wire 1 } a $end
$var wire 1 r b $end
$var wire 1 s y $end
$upscope $end
$upscope $end
$scope module u_fadd_13 $end
$var wire 1 ~ a $end
$var wire 1 !" b $end
$var wire 1 "" cin $end
$var wire 1 #" s $end
$var wire 4 $" n [3:0] $end
$var wire 1 %" cout $end
$scope module u_and2_0 $end
$var wire 1 ~ a $end
$var wire 1 !" b $end
$var wire 1 &" y $end
$upscope $end
$scope module u_and2_1 $end
$var wire 1 ~ a $end
$var wire 1 "" b $end
$var wire 1 '" y $end
$upscope $end
$scope module u_and2_2 $end
$var wire 1 !" a $end
$var wire 1 "" b $end
$var wire 1 (" y $end
$upscope $end
$scope module u_or3_0 $end
$var wire 1 )" a $end
$var wire 1 *" b $end
$var wire 1 +" c $end
$var wire 1 %" y $end
$upscope $end
$scope module u_xor2_0 $end
$var wire 1 ~ a $end
$var wire 1 !" b $end
$var wire 1 ," y $end
$upscope $end
$scope module u_xor2_1 $end
$var wire 1 -" a $end
$var wire 1 "" b $end
$var wire 1 #" y $end
$upscope $end
$upscope $end
$scope module u_fadd_14 $end
$var wire 1 ." a $end
$var wire 1 /" b $end
$var wire 1 0" cin $end
$var wire 1 1" s $end
$var wire 4 2" n [3:0] $end
$var wire 1 3" cout $end
$scope module u_and2_0 $end
$var wire 1 ." a $end
$var wire 1 /" b $end
$var wire 1 4" y $end
$upscope $end
$scope module u_and2_1 $end
$var wire 1 ." a $end
$var wire 1 0" b $end
$var wire 1 5" y $end
$upscope $end
$scope module u_and2_2 $end
$var wire 1 /" a $end
$var wire 1 0" b $end
$var wire 1 6" y $end
$upscope $end
$scope module u_or3_0 $end
$var wire 1 7" a $end
$var wire 1 8" b $end
$var wire 1 9" c $end
$var wire 1 3" y $end
$upscope $end
$scope module u_xor2_0 $end
$var wire 1 ." a $end
$var wire 1 /" b $end
$var wire 1 :" y $end
$upscope $end
$scope module u_xor2_1 $end
$var wire 1 ;" a $end
$var wire 1 0" b $end
$var wire 1 1" y $end
$upscope $end
$upscope $end
$scope module u_fadd_15 $end
$var wire 1 <" a $end
$var wire 1 =" b $end
$var wire 1 >" cin $end
$var wire 1 ?" s $end
$var wire 4 @" n [3:0] $end
$var wire 1 A" cout $end
$scope module u_and2_0 $end
$var wire 1 <" a $end
$var wire 1 =" b $end
$var wire 1 B" y $end
$upscope $end
$scope module u_and2_1 $end
$var wire 1 <" a $end
$var wire 1 >" b $end
$var wire 1 C" y $end
$upscope $end
$scope module u_and2_2 $end
$var wire 1 =" a $end
$var wire 1 >" b $end
$var wire 1 D" y $end
$upscope $end
$scope module u_or3_0 $end
$var wire 1 E" a $end
$var wire 1 F" b $end
$var wire 1 G" c $end
$var wire 1 A" y $end
$upscope $end
$scope module u_xor2_0 $end
$var wire 1 <" a $end
$var wire 1 =" b $end
$var wire 1 H" y $end
$upscope $end
$scope module u_xor2_1 $end
$var wire 1 I" a $end
$var wire 1 >" b $end
$var wire 1 ?" y $end
$upscope $end
$upscope $end
$scope module u_fadd_2 $end
$var wire 1 J" a $end
$var wire 1 K" b $end
$var wire 1 L" cin $end
$var wire 1 M" s $end
$var wire 4 N" n [3:0] $end
$var wire 1 O" cout $end
$scope module u_and2_0 $end
$var wire 1 J" a $end
$var wire 1 K" b $end
$var wire 1 P" y $end
$upscope $end
$scope module u_and2_1 $end
$var wire 1 J" a $end
$var wire 1 L" b $end
$var wire 1 Q" y $end
$upscope $end
$scope module u_and2_2 $end
$var wire 1 K" a $end
$var wire 1 L" b $end
$var wire 1 R" y $end
$upscope $end
$scope module u_or3_0 $end
$var wire 1 S" a $end
$var wire 1 T" b $end
$var wire 1 U" c $end
$var wire 1 O" y $end
$upscope $end
$scope module u_xor2_0 $end
$var wire 1 J" a $end
$var wire 1 K" b $end
$var wire 1 V" y $end
$upscope $end
$scope module u_xor2_1 $end
$var wire 1 W" a $end
$var wire 1 L" b $end
$var wire 1 M" y $end
$upscope $end
$upscope $end
$scope module u_fadd_3 $end
$var wire 1 X" a $end
$var wire 1 Y" b $end
$var wire 1 Z" cin $end
$var wire 1 [" s $end
$var wire 4 \" n [3:0] $end
$var wire 1 ]" cout $end
$scope module u_and2_0 $end
$var wire 1 X" a $end
$var wire 1 Y" b $end
$var wire 1 ^" y $end
$upscope $end
$scope module u_and2_1 $end
$var wire 1 X" a $end
$var wire 1 Z" b $end
$var wire 1 _" y $end
$upscope $end
$scope module u_and2_2 $end
$var wire 1 Y" a $end
$var wire 1 Z" b $end
$var wire 1 `" y $end
$upscope $end
$scope module u_or3_0 $end
$var wire 1 a" a $end
$var wire 1 b" b $end
$var wire 1 c" c $end
$var wire 1 ]" y $end
$upscope $end
$scope module u_xor2_0 $end
$var wire 1 X" a $end
$var wire 1 Y" b $end
$var wire 1 d" y $end
$upscope $end
$scope module u_xor2_1 $end
$var wire 1 e" a $end
$var wire 1 Z" b $end
$var wire 1 [" y $end
$upscope $end
$upscope $end
$scope module u_fadd_4 $end
$var wire 1 f" a $end
$var wire 1 g" b $end
$var wire 1 h" cin $end
$var wire 1 i" s $end
$var wire 4 j" n [3:0] $end
$var wire 1 k" cout $end
$scope module u_and2_0 $end
$var wire 1 f" a $end
$var wire 1 g" b $end
$var wire 1 l" y $end
$upscope $end
$scope module u_and2_1 $end
$var wire 1 f" a $end
$var wire 1 h" b $end
$var wire 1 m" y $end
$upscope $end
$scope module u_and2_2 $end
$var wire 1 g" a $end
$var wire 1 h" b $end
$var wire 1 n" y $end
$upscope $end
$scope module u_or3_0 $end
$var wire 1 o" a $end
$var wire 1 p" b $end
$var wire 1 q" c $end
$var wire 1 k" y $end
$upscope $end
$scope module u_xor2_0 $end
$var wire 1 f" a $end
$var wire 1 g" b $end
$var wire 1 r" y $end
$upscope $end
$scope module u_xor2_1 $end
$var wire 1 s" a $end
$var wire 1 h" b $end
$var wire 1 i" y $end
$upscope $end
$upscope $end
$scope module u_fadd_5 $end
$var wire 1 t" a $end
$var wire 1 u" b $end
$var wire 1 v" cin $end
$var wire 1 w" s $end
$var wire 4 x" n [3:0] $end
$var wire 1 y" cout $end
$scope module u_and2_0 $end
$var wire 1 t" a $end
$var wire 1 u" b $end
$var wire 1 z" y $end
$upscope $end
$scope module u_and2_1 $end
$var wire 1 t" a $end
$var wire 1 v" b $end
$var wire 1 {" y $end
$upscope $end
$scope module u_and2_2 $end
$var wire 1 u" a $end
$var wire 1 v" b $end
$var wire 1 |" y $end
$upscope $end
$scope module u_or3_0 $end
$var wire 1 }" a $end
$var wire 1 ~" b $end
$var wire 1 !# c $end
$var wire 1 y" y $end
$upscope $end
$scope module u_xor2_0 $end
$var wire 1 t" a $end
$var wire 1 u" b $end
$var wire 1 "# y $end
$upscope $end
$scope module u_xor2_1 $end
$var wire 1 ## a $end
$var wire 1 v" b $end
$var wire 1 w" y $end
$upscope $end
$upscope $end
$scope module u_fadd_6 $end
$var wire 1 $# a $end
$var wire 1 %# b $end
$var wire 1 &# cin $end
$var wire 1 '# s $end
$var wire 4 (# n [3:0] $end
$var wire 1 )# cout $end
$scope module u_and2_0 $end
$var wire 1 $# a $end
$var wire 1 %# b $end
$var wire 1 *# y $end
$upscope $end
$scope module u_and2_1 $end
$var wire 1 $# a $end
$var wire 1 &# b $end
$var wire 1 +# y $end
$upscope $end
$scope module u_and2_2 $end
$var wire 1 %# a $end
$var wire 1 &# b $end
$var wire 1 ,# y $end
$upscope $end
$scope module u_or3_0 $end
$var wire 1 -# a $end
$var wire 1 .# b $end
$var wire 1 /# c $end
$var wire 1 )# y $end
$upscope $end
$scope module u_xor2_0 $end
$var wire 1 $# a $end
$var wire 1 %# b $end
$var wire 1 0# y $end
$upscope $end
$scope module u_xor2_1 $end
$var wire 1 1# a $end
$var wire 1 &# b $end
$var wire 1 '# y $end
$upscope $end
$upscope $end
$scope module u_fadd_7 $end
$var wire 1 2# a $end
$var wire 1 3# b $end
$var wire 1 4# cin $end
$var wire 1 5# s $end
$var wire 4 6# n [3:0] $end
$var wire 1 7# cout $end
$scope module u_and2_0 $end
$var wire 1 2# a $end
$var wire 1 3# b $end
$var wire 1 8# y $end
$upscope $end
$scope module u_and2_1 $end
$var wire 1 2# a $end
$var wire 1 4# b $end
$var wire 1 9# y $end
$upscope $end
$scope module u_and2_2 $end
$var wire 1 3# a $end
$var wire 1 4# b $end
$var wire 1 :# y $end
$upscope $end
$scope module u_or3_0 $end
$var wire 1 ;# a $end
$var wire 1 <# b $end
$var wire 1 =# c $end
$var wire 1 7# y $end
$upscope $end
$scope module u_xor2_0 $end
$var wire 1 2# a $end
$var wire 1 3# b $end
$var wire 1 ># y $end
$upscope $end
$scope module u_xor2_1 $end
$var wire 1 ?# a $end
$var wire 1 4# b $end
$var wire 1 5# y $end
$upscope $end
$upscope $end
$scope module u_fadd_8 $end
$var wire 1 @# a $end
$var wire 1 A# b $end
$var wire 1 B# cin $end
$var wire 1 C# s $end
$var wire 4 D# n [3:0] $end
$var wire 1 E# cout $end
$scope module u_and2_0 $end
$var wire 1 @# a $end
$var wire 1 A# b $end
$var wire 1 F# y $end
$upscope $end
$scope module u_and2_1 $end
$var wire 1 @# a $end
$var wire 1 B# b $end
$var wire 1 G# y $end
$upscope $end
$scope module u_and2_2 $end
$var wire 1 A# a $end
$var wire 1 B# b $end
$var wire 1 H# y $end
$upscope $end
$scope module u_or3_0 $end
$var wire 1 I# a $end
$var wire 1 J# b $end
$var wire 1 K# c $end
$var wire 1 E# y $end
$upscope $end
$scope module u_xor2_0 $end
$var wire 1 @# a $end
$var wire 1 A# b $end
$var wire 1 L# y $end
$upscope $end
$scope module u_xor2_1 $end
$var wire 1 M# a $end
$var wire 1 B# b $end
$var wire 1 C# y $end
$upscope $end
$upscope $end
$scope module u_fadd_9 $end
$var wire 1 N# a $end
$var wire 1 O# b $end
$var wire 1 P# cin $end
$var wire 1 Q# s $end
$var wire 4 R# n [3:0] $end
$var wire 1 S# cout $end
$scope module u_and2_0 $end
$var wire 1 N# a $end
$var wire 1 O# b $end
$var wire 1 T# y $end
$upscope $end
$scope module u_and2_1 $end
$var wire 1 N# a $end
$var wire 1 P# b $end
$var wire 1 U# y $end
$upscope $end
$scope module u_and2_2 $end
$var wire 1 O# a $end
$var wire 1 P# b $end
$var wire 1 V# y $end
$upscope $end
$scope module u_or3_0 $end
$var wire 1 W# a $end
$var wire 1 X# b $end
$var wire 1 Y# c $end
$var wire 1 S# y $end
$upscope $end
$scope module u_xor2_0 $end
$var wire 1 N# a $end
$var wire 1 O# b $end
$var wire 1 Z# y $end
$upscope $end
$scope module u_xor2_1 $end
$var wire 1 [# a $end
$var wire 1 P# b $end
$var wire 1 Q# y $end
$upscope $end
$upscope $end
$upscope $end
$upscope $end
$enddefinitions $end
$comment Show the parameter values. $end
$dumpall
$end
#0
$dumpvars
x[#
xZ#
xY#
xX#
xW#
xV#
xU#
xT#
xS#
bx R#
xQ#
xP#
0O#
0N#
xM#
xL#
xK#
xJ#
xI#
xH#
xG#
xF#
xE#
bx D#
xC#
xB#
0A#
0@#
x?#
x>#
x=#
x<#
x;#
x:#
x9#
x8#
x7#
bx 6#
x5#
x4#
03#
02#
x1#
x0#
x/#
x.#
x-#
x,#
x+#
x*#
x)#
bx (#
x'#
x&#
0%#
0$#
x##
x"#
x!#
x~"
x}"
x|"
x{"
xz"
xy"
bx x"
xw"
xv"
0u"
0t"
xs"
xr"
xq"
xp"
xo"
xn"
xm"
xl"
xk"
bx j"
xi"
xh"
0g"
0f"
xe"
xd"
xc"
xb"
xa"
x`"
x_"
x^"
x]"
bx \"
x["
xZ"
0Y"
0X"
xW"
xV"
xU"
xT"
xS"
xR"
xQ"
xP"
xO"
bx N"
xM"
xL"
0K"
0J"
xI"
xH"
xG"
xF"
xE"
xD"
xC"
xB"
xA"
bx @"
x?"
x>"
0="
0<"
x;"
x:"
x9"
x8"
x7"
x6"
x5"
x4"
x3"
bx 2"
x1"
x0"
0/"
0."
x-"
x,"
x+"
x*"
x)"
x("
x'"
x&"
x%"
bx $"
x#"
x""
0!"
0~
x}
x|
x{
xz
xy
xx
xw
xv
xu
bx t
xs
xr
0q
0p
xo
xn
xm
xl
xk
xj
xi
xh
xg
bx f
xe
xd
0c
0b
xa
x`
x_
x^
x]
x\
x[
xZ
xY
bx X
xW
xV
0U
0T
xS
xR
xQ
xP
xO
xN
xM
xL
xK
bx J
xI
xH
0G
0F
xE
xD
xC
xB
xA
x@
x?
x>
x=
bx <
x;
0:
09
b0 8
07
b0 6
b0 5
bx 4
bx 3
b0 2
b0 1
b10000000000000000000000000000011 0
0/
1.
0-
0,
0+
b0 *
b0 )
b0 (
b0 '
b0 &
b0 %
0$
0#
b0 "
b0 !
$end
#10
0E
0S
0W"
0e"
0s"
0##
01#
0?#
0M#
0[#
0a
0o
0}
0-"
0;"
0I"
bx0 <
0D
bx0 J
0R
bx0 N"
0V"
bx0 \"
0d"
bx0 j"
0r"
bx0 x"
0"#
bx0 (#
00#
bx0 6#
0>#
bx0 D#
0L#
bx0 R#
0Z#
bx0 X
0`
bx0 f
0n
bx0 t
0|
bx0 $"
0,"
bx0 2"
0:"
bx0 @"
0H"
#15
0Q
0U"
0c"
0q"
0!#
0/#
0=#
0K#
0Y#
0_
0m
0{
0+"
09"
0G"
0A
0O
0P
0S"
0T"
0a"
0b"
0o"
0p"
0}"
0~"
0-#
0.#
0;#
0<#
0I#
0J#
0W#
0X#
0]
0^
0k
0l
0y
0z
0)"
0*"
07"
08"
0E"
0F"
0B
0C
0N
0R"
0`"
0n"
0|"
0,#
0:#
0H#
0V#
0\
0j
0x
0("
06"
0D"
0>
0L
b0 J
0M
0P"
b0 N"
0Q"
0^"
b0 \"
0_"
0l"
b0 j"
0m"
0z"
b0 x"
0{"
0*#
b0 (#
0+#
08#
b0 6#
09#
0F#
b0 D#
0G#
0T#
b0 R#
0U#
0Z
b0 X
0[
0h
b0 f
0i
0v
b0 t
0w
0&"
b0 $"
0'"
04"
b0 2"
05"
0B"
b0 @"
0C"
0?
b0 <
0@
#20
bx0 3
0;
#31
0H
0L"
0Z"
0h"
0v"
0&#
04#
0B#
0P#
0V
0d
0r
0""
00"
0>"
0=
0K
0O"
0]"
0k"
0y"
0)#
07#
0E#
0S#
0Y
0g
0u
0%"
03"
b0 4
0A"
#41
0I
0M"
0["
0i"
0w"
0'#
05#
0C#
0Q#
0W
0e
0s
0#"
01"
b0 3
0?"
#252
0.
#504
1.
#756
0.
#1008
1.
#1009
1/
#1260
0.
#1512
1.
#1764
0.
#2016
1.
#2017
b1111111111111111 (
b1111111111111111 2
#2268
0.
#2520
1.
#2521
b1111111111111111 )
1+
#2530
1:
1G
1K"
1Y"
1g"
1u"
1%#
13#
1A#
1O#
1U
1c
1q
1!"
1/"
1="
b1111111111111111 6
#2540
1E
1S
1W"
1e"
1s"
1##
11#
1?#
1M#
1[#
1a
1o
1}
1-"
1;"
1I"
b1 <
1D
b1 J
1R
b1 N"
1V"
b1 \"
1d"
b1 j"
1r"
b1 x"
1"#
b1 (#
10#
b1 6#
1>#
b1 D#
1L#
b1 R#
1Z#
b1 X
1`
b1 f
1n
b1 t
1|
b1 $"
1,"
b1 2"
1:"
b1 @"
1H"
#2550
1;
1I
1M"
1["
1i"
1w"
1'#
15#
1C#
1Q#
1W
1e
1s
1#"
11"
b1111111111111111 3
1?"
#2772
0.
#3024
1.
#3025
b1111111111111111 !
b1111111111111111 *
1,
b1 %
b1 1
#3034
17
b1111111111111111 "
b1111111111111111 8
#3044
b1111111111111110 3
0;
#3049
1C
b1001 <
1@
#3065
1H
b1 4
1=
#3075
b1111111111111100 3
0I
#3080
1Q
b1001 J
1N
#3096
1L"
b11 4
1K
#3106
b1111111111111000 3
0M"
#3111
1U"
b1001 N"
1R"
#3127
1Z"
b111 4
1O"
#3137
b1111111111110000 3
0["
#3142
1c"
b1001 \"
1`"
#3158
1h"
b1111 4
1]"
#3168
b1111111111100000 3
0i"
#3173
1q"
b1001 j"
1n"
#3189
1v"
b11111 4
1k"
#3199
b1111111111000000 3
0w"
#3204
1!#
b1001 x"
1|"
#3220
1&#
b111111 4
1y"
#3230
b1111111110000000 3
0'#
#3235
1/#
b1001 (#
1,#
#3251
14#
b1111111 4
1)#
#3261
b1111111100000000 3
05#
#3266
1=#
b1001 6#
1:#
#3276
0.
#3282
1B#
b11111111 4
17#
#3292
b1111111000000000 3
0C#
#3297
1K#
b1001 D#
1H#
#3313
1P#
b111111111 4
1E#
#3323
b1111110000000000 3
0Q#
#3328
1Y#
b1001 R#
1V#
#3344
1V
b1111111111 4
1S#
#3354
b1111100000000000 3
0W
#3359
1_
b1001 X
1\
#3375
1d
b11111111111 4
1Y
#3385
b1111000000000000 3
0e
#3390
1m
b1001 f
1j
#3406
1r
b111111111111 4
1g
#3416
b1110000000000000 3
0s
#3421
1{
b1001 t
1x
#3437
1""
b1111111111111 4
1u
#3447
b1100000000000000 3
0#"
#3452
1+"
b1001 $"
1("
#3468
10"
b11111111111111 4
1%"
#3478
b1000000000000000 3
01"
#3483
19"
b1001 2"
16"
#3499
1>"
b111111111111111 4
13"
#3509
b0 3
0?"
#3514
1G"
b1001 @"
1D"
#3528
1.
#3529
b0 !
1#
1-
b1 &
b10 %
b10 1
#3530
b1111111111111111 4
1A"
#3538
19
b0 "
b0 8
b1 5
#3548
0E
b1000 <
0D
#3553
1A
1B
1>
b1110 <
1?
#3558
b1 3
1;
#3780
0.
#4032
1.
