COSE221_Digital_Logic_Design/Lab #3/fsm2.sv
/* *******************************
 *	COSE221 Lab #3
 *
 *	Author: Gunjae Koo (gunjaekoo@korea.ac.kr)
 *
 * *******************************
 */

module fsm2(
	input			clk,
	input			reset_n,	// asychronous negative reset
	input			p, r,
	input			ta, tb,
	output	[1:0]	la, lb
);

	logic			m;

	fsm_mode u_mode_0(
		.clk(clk),
		.reset_n(reset_n),
		.p(p),
		.r(r),
		.m(m)
	);

	fsm_light u_light_0(
		.clk(clk),
		.reset_n(reset_n),
		.m(m),
		.ta(ta),
		.tb(tb),
		.la(la),
		.lb(lb)
	);


endmodule

module fsm_mode(
	input			clk,
	input			reset_n,	// asychronous negative reset
	input			p, r,
	output			m
);

	localparam S0 = 1'b0,
			   S1 = 1'b1;

	logic			state_curr, state_next;

	// state register
	always_ff @( posedge clk or negedge reset_n ) begin
		if (~reset_n)	state_curr <= S0;
		else			state_curr <= state_next;
	end

	// next state logic
	always_comb begin
		case (state_curr)
			S0 : state_next = p ? S1 : S0;
			S1 : state_next = r ? S0 : S1;
		endcase
	end

	// output logic
	assign m = state_curr == S0 ? 1'b0 : 1'b1;

	// synthesis translate_off
	logic [2*8-1:0] state_dbg;

	always_comb begin
		case (state_curr)
			S0: state_dbg = "S0";
			S1: state_dbg = "S1";
		endcase
	end
	// synthesis translate_on

endmodule

module fsm_light(
	input			clk,
	input			reset_n,	// asychronous negative reset
	input			m,
	input			ta, tb,
	output	[1:0]	la, lb
);

	logic	[1:0]	la, lb;

	localparam S0 = 2'b00,
		       S1 = 2'b01,
			   S2 = 2'b10,
			   S3 = 2'b11;

	localparam GREEN = 2'b00,
		       YELLOW = 2'b01,
			   RED = 2'b10;

	logic [1:0]	state_curr, state_next;

	// state register
	always_ff @( posedge clk or negedge reset_n ) begin
		if (~reset_n)	state_curr <= S0;
		else			state_curr <= state_next;
	end

	// next state logic
	always_comb begin
		case (state_curr)
			S0 : state_next = ta ? S0 : S1;
			S1 : state_next = S2;
			S2 : state_next = m | tb ? S2 : S3;
			S3 : state_next = S0;
		endcase
	end

	// output logic
	always_comb begin
		case (state_curr)
			S0 : begin
				la = GREEN;
				lb = RED;
			end
			S1 : begin
				la = YELLOW;
				lb = RED;
			end
			S2 : begin
				la = RED;
				lb = GREEN;
			end
			S3 : begin
				la = RED;
				lb = YELLOW;
			end
		endcase
	end

	// synthesis translate_off
	logic [2*8-1:0] state_dbg;

	always_comb begin
		case (state_curr)
			S0: state_dbg = "S0";
			S1: state_dbg = "S1";
			S2: state_dbg = "S2";
			S3: state_dbg = "S3";
		endcase
	end
	// synthesis translate_on

endmodule

COSE221_Digital_Logic_Design/Lab #3/tb_fsm2.sv
/* ************************
 *	COSE221 Lab #3
 *
 *	Author: Gunjae Koo (gunjaekoo2@korea.ac.kr)
 * ************************
 */

`timescale 1ns/1ps
`define CLK_T 10
module tb_fsm2();

	integer f;
	logic 		clk, reset_b;

	initial clk = 1'b1;
	always #(`CLK_T/2) clk = ~clk;

	logic 		ta, tb;
	logic		p, r;
	logic [1:0] la, lb;

	initial begin
		$dumpfile("tb_fsm2.vcd");
		$dumpvars(0, tb_fsm2);
		f = $fopen("tb_fsm2.out", "w");
		
		reset_b = 1'b0;
		ta = 1'b1; tb = 1'b0; p = 1'b0; r = 1'b0;
		repeat (2) @ (posedge clk);
		#(1) reset_b = 1'b1;
		repeat (2) @ (posedge clk);
		#(1) ta = 1'b1; tb = 1'b1; p = 1'b1; r = 1'b0;
		repeat (2) @ (posedge clk);
		#(1) ta = 1'b0; tb = 1'b1;
		repeat (4) @ (posedge clk);
		#(1) ta = 1'b1; tb = 1'b1;
		repeat (2) @ (posedge clk);
		#(1) ta = 1'b1; tb = 1'b0; p = 1'b0; r = 1'b1;
		repeat (4) @ (posedge clk);
		#(1) ta = 1'b0; tb = 1'b0;
		repeat (5) @ (posedge clk);

		$fclose(f);
		$finish(1);
	end


	always @ (negedge clk) begin
		$write("%02b, %02b @ %2.3f\n", la, lb, $realtime);
		$fwrite(f, "%02b, %02b @ %2.3f\n", la, lb, $realtime);
	end

	fsm2 dut (clk, reset_b, p, r, ta, tb, la, lb);

endmodule

COSE221_Digital_Logic_Design/Lab #3/tb_fsm2.vcd
$date
	Thu May 18 20:13:50 2023
$end
$version
	Icarus Verilog
$end
$timescale
	1ps
$end
$scope module tb_fsm2 $end
$var wire 2 ! lb [1:0] $end
$var wire 2 " la [1:0] $end
$var reg 1 # clk $end
$var reg 1 $ p $end
$var reg 1 % r $end
$var reg 1 & reset_b $end
$var reg 1 ' ta $end
$var reg 1 ( tb $end
$var integer 32 ) f [31:0] $end
$scope module dut $end
$var wire 1 # clk $end
$var wire 1 $ p $end
$var wire 1 % r $end
$var wire 1 & reset_n $end
$var wire 1 ' ta $end
$var wire 1 ( tb $end
$var wire 1 * m $end
$var wire 2 + lb [1:0] $end
$var wire 2 , la [1:0] $end
$scope module u_light_0 $end
$var wire 1 # clk $end
$var wire 1 & reset_n $end
$var wire 1 ' ta $end
$var wire 1 ( tb $end
$var wire 1 * m $end
$var parameter 2 - GREEN $end
$var parameter 2 . RED $end
$var parameter 2 / S0 $end
$var parameter 2 0 S1 $end
$var parameter 2 1 S2 $end
$var parameter 2 2 S3 $end
$var parameter 2 3 YELLOW $end
$var reg 2 4 la [1:0] $end
$var reg 2 5 lb [1:0] $end
$var reg 2 6 state_curr [1:0] $end
$var reg 16 7 state_dbg [15:0] $end
$var reg 2 8 state_next [1:0] $end
$upscope $end
$scope module u_mode_0 $end
$var wire 1 # clk $end
$var wire 1 $ p $end
$var wire 1 % r $end
$var wire 1 & reset_n $end
$var wire 1 * m $end
$var parameter 1 9 S0 $end
$var parameter 1 : S1 $end
$var reg 1 ; state_curr $end
$var reg 16 < state_dbg [15:0] $end
$var reg 1 = state_next $end
$upscope $end
$upscope $end
$upscope $end
$enddefinitions $end
$comment Show the parameter values. $end
$dumpall
1:
09
b1 3
b11 2
b10 1
b1 0
b0 /
b10 .
b0 -
$end
#0
$dumpvars
0=
b101001100110000 <
0;
b0 8
b101001100110000 7
b0 6
b10 5
b0 4
b0 ,
b10 +
0*
b10000000000000000000000000000011 )
0(
1'
0&
0%
0$
1#
b0 "
b10 !
$end
#5000
0#
#10000
1#
#15000
0#
#20000
1#
#21000
1&
#25000
0#
#30000
1#
#35000
0#
#40000
1#
#41000
1=
1$
1(
#45000
0#
#50000
1*
b101001100110001 <
1;
1#
#55000
0#
#60000
1#
#61000
b1 8
0'
#65000
0#
#70000
b1 "
b1 ,
b1 4
b101001100110001 7
b10 8
b1 6
1#
#75000
0#
#80000
b0 !
b0 +
b0 5
b10 "
b10 ,
b10 4
b101001100110010 7
b10 6
1#
#85000
0#
#90000
1#
#95000
0#
#100000
1#
#101000
1'
#105000
0#
#110000
1#
#115000
0#
#120000
1#
#121000
0=
1%
0$
0(
#125000
0#
#130000
b11 8
0*
b101001100110000 <
0;
1#
#135000
0#
#140000
b1 !
b1 +
b1 5
b101001100110011 7
b0 8
b11 6
1#
#145000
0#
#150000
b10 !
b10 +
b10 5
b0 "
b0 ,
b0 4
b101001100110000 7
b0 6
1#
#155000
0#
#160000
1#
#161000
b1 8
0'
#165000
0#
#170000
b1 "
b1 ,
b1 4
b101001100110001 7
b10 8
b1 6
1#
#175000
0#
#180000
b0 !
b0 +
b0 5
b10 "
b10 ,
b10 4
b101001100110010 7
b11 8
b10 6
1#
#185000
0#
#190000
b1 !
b1 +
b1 5
b101001100110011 7
b0 8
b11 6
1#
#195000
0#
#200000
b10 !
b10 +
b10 5
b0 "
b0 ,
b0 4
b101001100110000 7
b1 8
b0 6
1#
#205000
0#
#210000
b1 "
b1 ,
b1 4
b101001100110001 7
b10 8
b1 6
1#
