COSE221_Digital_Logic_Design/Lab #2/test4.sv
/* *******************************
 *	COSE221 Lab #2
 *
 *	Author: Gunjae Koo (gunjaekoo@korea.ac.kr)
 *
 * *******************************
 */

module tristate(a, en, y);
	input			a, en;
	output	tri		y;

	assign y = (en) ? a: 1'bZ;
endmodule

module mux2(a, b, sel, y);
	input			a, b, sel;
	output	tri		y;

	/* FILL THIS */
	tristate u_tristate_0 (a, ~sel, y);
	tristate u_tristate_1 (b, sel, y);

endmodule

module test4(a, b, y, good);
	input			a, b, y;
	output	tri		good;

	/* INTERNAL NODES (TO BE DECLARED AS 'tri' TYPES) */
	tri		c, d, e;
	/* FILL THIS (STRUCTURAL MODEL) */
	mux2 u_mux2_c (1, 0, y, c);
	mux2 u_mux2_d (y, y, b, d);
	mux2 u_mux2_e (y, c, b, e);
	mux2 u_mux2_g (d, e, a, good);

endmodule

COSE221_Digital_Logic_Design/Lab #2/tb_test4.sv
/* ************************
 *	COSE221 Lab #2
 *
 *	Author: Gunjae Koo (gunjaekoo2@korea.ac.kr)
 * ************************
 */

`timescale 1ns/1ps
module tb_test4();

	logic a = 'b0;
	logic b = 'b0;
	logic y = 'b0;
	tri good;		// should be a 'tri' type
	
	always #(5) a = ~a;
	always #(10) b = ~b;
	always #(20) y = ~y;

	integer f;
	logic clk = 1'b0;	// for sampling
	always #(2.5) clk = ~clk;

	always @ (posedge clk) begin
		$write("%1b, %1b, %1b; %1b @ %2.3f\n", a, b, y, good, $realtime);
		$fwrite(f, "%1b, %1b, %1b; %1b @ %2.3f\n", a, b, y, good, $realtime);
	end

	initial begin
		$dumpfile("tb_test4.vcd");
		$dumpvars(0, tb_test4);
		f = $fopen("tb_test4.out", "w");
		#(45)
		$fclose(f);
		$finish;
	end

	test4 dut (a, b, y, good);

endmodule

COSE221_Digital_Logic_Design/Lab #2/tb_test4.vcd
$date
	Sat May 13 20:50:06 2023
$end
$version
	Icarus Verilog
$end
$timescale
	1ps
$end
$scope module tb_test4 $end
$var wire 1 ! good $end
$var reg 1 " a $end
$var reg 1 # b $end
$var reg 1 $ clk $end
$var reg 1 % y $end
$var integer 32 & f [31:0] $end
$scope module dut $end
$var wire 1 " a $end
$var wire 1 # b $end
$var wire 1 ' c $end
$var wire 1 ( d $end
$var wire 1 ) e $end
$var wire 1 ! good $end
$var wire 1 % y $end
$scope module u_mux2_c $end
$var wire 1 * a $end
$var wire 1 + b $end
$var wire 1 % sel $end
$var wire 1 ' y $end
$scope module u_tristate_0 $end
$var wire 1 * a $end
$var wire 1 , en $end
$var wire 1 ' y $end
$upscope $end
$scope module u_tristate_1 $end
$var wire 1 + a $end
$var wire 1 % en $end
$var wire 1 ' y $end
$upscope $end
$upscope $end
$scope module u_mux2_d $end
$var wire 1 % a $end
$var wire 1 % b $end
$var wire 1 # sel $end
$var wire 1 ( y $end
$scope module u_tristate_0 $end
$var wire 1 % a $end
$var wire 1 - en $end
$var wire 1 ( y $end
$upscope $end
$scope module u_tristate_1 $end
$var wire 1 % a $end
$var wire 1 # en $end
$var wire 1 ( y $end
$upscope $end
$upscope $end
$scope module u_mux2_e $end
$var wire 1 % a $end
$var wire 1 ' b $end
$var wire 1 # sel $end
$var wire 1 ) y $end
$scope module u_tristate_0 $end
$var wire 1 % a $end
$var wire 1 . en $end
$var wire 1 ) y $end
$upscope $end
$scope module u_tristate_1 $end
$var wire 1 ' a $end
$var wire 1 # en $end
$var wire 1 ) y $end
$upscope $end
$upscope $end
$scope module u_mux2_g $end
$var wire 1 ( a $end
$var wire 1 ) b $end
$var wire 1 " sel $end
$var wire 1 ! y $end
$scope module u_tristate_0 $end
$var wire 1 ( a $end
$var wire 1 / en $end
$var wire 1 ! y $end
$upscope $end
$scope module u_tristate_1 $end
$var wire 1 ) a $end
$var wire 1 " en $end
$var wire 1 ! y $end
$upscope $end
$upscope $end
$upscope $end
$upscope $end
$enddefinitions $end
$comment Show the parameter values. $end
$dumpall
$end
#0
$dumpvars
1/
1.
1-
1,
0+
1*
0)
0(
1'
b10000000000000000000000000000011 &
0%
0$
0#
0"
0!
$end
#2500
1$
#5000
0/
0$
1"
#7500
1$
#10000
1/
0!
0-
0.
1)
0$
0"
1#
#12500
1$
#15000
0/
1!
0$
1"
#17500
1$
#20000
1/
1!
1-
1.
1)
0,
0'
1(
0$
0"
0#
1%
#22500
1$
#25000
0/
0$
1"
#27500
1$
#30000
1/
1!
0-
0.
0)
0$
0"
1#
#32500
1$
#35000
0/
0!
0$
1"
#37500
1$
#40000
1/
0!
1-
1.
0)
1,
1'
0(
0$
0"
0#
0%
#42500
1$
#45000
0/
0$
1"
