COSE221_Digital_Logic_Design/Lab #2/test2.sv
/* *******************************
 *	COSE221 Lab #2
 *
 *	Author: Gunjae Koo (gunjaekoo@korea.ac.kr)
 *
 * *******************************
 */

module test2(a, b, y, good);
	input			a, b, y;
	output			good;

	/* INTERNAL NODES */
	wire c, d, e;
	/* FILL THIS */
	assign c = y ? 0 : 1;
	assign d = y;
	assign e = b ? c : y;
	assign good = a ? e : d;

endmodule

COSE221_Digital_Logic_Design/Lab #2/tb_test2.sv
/* ************************
 *	COSE221 Lab #2
 *
 *	Author: Gunjae Koo (gunjaekoo2@korea.ac.kr)
 * ************************
 */

`timescale 1ns/1ps
module tb_test2();

	logic a = 'b0;
	logic b = 'b0;
	logic y = 'b0;
	logic good;
	
	always #(5) a = ~a;
	always #(10) b = ~b;
	always #(20) y = ~y;
	
	integer f;
	logic clk = 1'b0;	// for sampling
	always #(2.5) clk = ~clk;

	always @ (posedge clk) begin
		$write("%1b, %1b, %1b; %1b @ %2.3f\n", a, b, y, good, $realtime);
		$fwrite(f, "%1b, %1b, %1b; %1b @ %2.3f\n", a, b, y, good, $realtime);
	end

	initial begin
		$dumpfile("tb_test2.vcd");
		$dumpvars(0, tb_test2);
		f = $fopen("tb_test2.out", "w");
		#(45)
		$fclose(f);
		$finish;
	end

	test2 dut (a, b, y, good);

endmodule

COSE221_Digital_Logic_Design/Lab #2/tb_test2.vcd
$date
	Sat May 13 20:30:07 2023
$end
$version
	Icarus Verilog
$end
$timescale
	1ps
$end
$scope module tb_test2 $end
$var wire 1 ! good $end
$var reg 1 " a $end
$var reg 1 # b $end
$var reg 1 $ clk $end
$var reg 1 % y $end
$var integer 32 & f [31:0] $end
$scope module dut $end
$var wire 1 " a $end
$var wire 1 # b $end
$var wire 1 ' d $end
$var wire 1 % y $end
$var wire 1 ! good $end
$var wire 1 ( e $end
$var wire 1 ) c $end
$upscope $end
$upscope $end
$enddefinitions $end
$comment Show the parameter values. $end
$dumpall
$end
#0
$dumpvars
1)
0(
0'
b10000000000000000000000000000011 &
0%
0$
0#
0"
0!
$end
#2500
1$
#5000
0$
1"
#7500
1$
#10000
1(
0$
0"
1#
#12500
1$
#15000
1!
0$
1"
#17500
1$
#20000
0)
0$
0"
0#
1'
1%
#22500
1$
#25000
0$
1"
#27500
1$
#30000
0(
0$
0"
1#
#32500
1$
#35000
0!
0$
1"
#37500
1$
#40000
1)
0$
0"
0#
0'
0%
#42500
1$
#45000
0$
1"
